bin/__init__.py
bin/noxrc.py
noxrunner/__init__.py
noxrunner/client.py
noxrunner/exceptions.py
noxrunner/py.typed
noxrunner/backend/__init__.py
noxrunner/backend/base.py
noxrunner/backend/http.py
noxrunner/backend/local.py
noxrunner/fileops/__init__.py
noxrunner/fileops/tar_handler.py
noxrunner/security/__init__.py
noxrunner/security/command_validator.py
noxrunner/security/path_sanitizer.py
noxrunner-2.0.0.dist-info/licenses/LICENSE
noxrunner-2.0.0.dist-info/METADATA
noxrunner-2.0.0.dist-info/WHEEL
noxrunner-2.0.0.dist-info/entry_points.txt
noxrunner-2.0.0.dist-info/top_level.txt
noxrunner-2.0.0.dist-info/RECORD
